LICENSE
MANIFEST.in
README.rst
setup.py
Orange_Textable.egg-info/PKG-INFO
Orange_Textable.egg-info/SOURCES.txt
Orange_Textable.egg-info/dependency_links.txt
Orange_Textable.egg-info/entry_points.txt
Orange_Textable.egg-info/not-zip-safe
Orange_Textable.egg-info/requires.txt
Orange_Textable.egg-info/top_level.txt
_textable/__init__.py
_textable/widgets/OWTextableCategory.py
_textable/widgets/OWTextableContext.py
_textable/widgets/OWTextableConvert.py
_textable/widgets/OWTextableCooccurrence.py
_textable/widgets/OWTextableCount.py
_textable/widgets/OWTextableDisplay.py
_textable/widgets/OWTextableExtractXML.py
_textable/widgets/OWTextableIntersect.py
_textable/widgets/OWTextableLength.py
_textable/widgets/OWTextableMerge.py
_textable/widgets/OWTextableMessage.py
_textable/widgets/OWTextablePreprocess.py
_textable/widgets/OWTextableRecode.py
_textable/widgets/OWTextableSegment.py
_textable/widgets/OWTextableSelect.py
_textable/widgets/OWTextableTextField.py
_textable/widgets/OWTextableTextFiles.py
_textable/widgets/OWTextableURLs.py
_textable/widgets/OWTextableVariety.py
_textable/widgets/TextableUtils.py
_textable/widgets/__init__.py
_textable/widgets/icons/Category-Textable.png
_textable/widgets/icons/Category_16.png
_textable/widgets/icons/Category_36.png
_textable/widgets/icons/Category_48.png
_textable/widgets/icons/Category_54.png
_textable/widgets/icons/Context_16.png
_textable/widgets/icons/Context_36.png
_textable/widgets/icons/Context_48.png
_textable/widgets/icons/Context_54.png
_textable/widgets/icons/Convert_16.png
_textable/widgets/icons/Convert_36.png
_textable/widgets/icons/Convert_48.png
_textable/widgets/icons/Convert_54.png
_textable/widgets/icons/Cooccurrence_16.png
_textable/widgets/icons/Cooccurrence_36.png
_textable/widgets/icons/Cooccurrence_48.png
_textable/widgets/icons/Cooccurrence_54.png
_textable/widgets/icons/Count_16.png
_textable/widgets/icons/Count_36.png
_textable/widgets/icons/Count_48.png
_textable/widgets/icons/Count_54.png
_textable/widgets/icons/Display_16.png
_textable/widgets/icons/Display_36.png
_textable/widgets/icons/Display_48.png
_textable/widgets/icons/Display_54.png
_textable/widgets/icons/ExtractXML_16.png
_textable/widgets/icons/ExtractXML_36.png
_textable/widgets/icons/ExtractXML_48.png
