Metadata-Version: 1.0
Name: Orange-Textable
Version: 2.0
Summary: Textable add-on for Orange 2.7 data mining software package.
Home-page: http://langtech.ch/textable
Author: LangTech Sarl
Author-email: info@langtech.ch
License: GPLv3
Download-URL: https://bitbucket.org/langtech/orange-textable/get/v2.0.zip
Keywords: text mining,text analysis,textable,orange,orange add-on
Platform: UNKNOWN
Classifier: Development Status :: 5 - Production/Stable
Classifier: Environment :: X11 Applications :: Qt
Classifier: Environment :: Plugins
Classifier: Programming Language :: Python
Classifier: License :: OSI Approved :: GNU General Public License v3 or later (GPLv3+)
Classifier: Operating System :: OS Independent
Classifier: Topic :: Scientific/Engineering :: Information Analysis
Classifier: Topic :: Text Processing :: General
Classifier: Topic :: Text Processing :: Linguistic
Classifier: Topic :: Software Development :: Libraries :: Python Modules
Classifier: Intended Audience :: Education
Classifier: Intended Audience :: Science/Research
